itzy/__init__.py
itzy/hello.py
itzy-0.0.2.dist-info/METADATA
itzy-0.0.2.dist-info/WHEEL
itzy-0.0.2.dist-info/licenses/LICENSE
itzy-0.0.2.dist-info/RECORD
