Metadata-Version: 2.4
Name: itzy
Version: 0.0.2
Summary: ITZY
Project-URL: Homepage, https://itzy.jype.com/
Author-email: jiquanbai <jiquanbai@gmail.com>
License-File: LICENSE
Classifier: License :: OSI Approved :: MIT License
Classifier: Operating System :: OS Independent
Classifier: Programming Language :: Python :: 3
Requires-Python: >=3.10
